{
    "companies": [
        {
            "name": "Amazon",
            "adminUser": {
                "name": "Francisco",
                "email": "f@amazon.com",
                "password": "123"
            },
            "employees": [
                {
                    "name": "Jeff",
                    "email": "j@amazon.com",
                    "password": "123",
                    "attendanceInfo": [
                        "Entrada: {21/2/2021, 21:30:16}"
                    ]
                },
                {
                    "name": "Milton",
                    "email": "m@amazon.com",
                    "password": "123",
                    "attendanceInfo": [
                        "Entrada: {20/2/2021, 20:39:00}"
                    ]
                },
                {
                    "name": "Andy",
                    "email": "a@amazon.com",
                    "password": "123",
                    "attendanceInfo": [
                        "Entrada: {20/2/2021, 20:59:58}",
                        "Saida: {21/2/2021, 21:00:07}",
                        "Entrada: {21/2/2021, 21:00:16}",
                        "Saida: {21/2/2021, 21:24:33}",
                        "Entrada: {21/2/2021, 21:27:58}"
                    ]
                },
                {
                    "name": "Gilson",
                    "email": "g@amazon.com",
                    "password": "123",
                    "attendanceInfo": [
                        "Entrada: {20/2/2021, 20:56:58}",
                        "Saida: {20/2/2021, 20:57:16}"
                    ]
                }
            ]
        },
        {
            "name": "Tecnogate",
            "adminUser": {
                "name": "Paulo",
                "email": "paulo@tecnogate.com.br",
                "password": "123"
            },
            "employees": [
                {
                    "name": "Fulano da Silva",
                    "email": "f@tecnogate.com.br",
                    "password": "123",
                    "attendanceInfo": []
                },
                {
                    "name": "Joao",
                    "email": "j@tecnogate.com.br",
                    "password": "123",
                    "attendanceInfo": []
                },
                {
                    "name": "Andre",
                    "email": "a@tecnogate.com.br",
                    "password": "123",
                    "attendanceInfo": []
                }
            ]
        },
        {
            "name": "Lets Code",
            "adminUser": {
                "name": "Pietro",
                "email": "p@letscode.com.br",
                "password": "123"
            },
            "employees": [
                {
                    "name": "Lucas",
                    "email": "l@letscode.com.br",
                    "password": "123",
                    "attendanceInfo": [
                        "Entrada: {21/2/2021, 21:31:18}",
                        "Saida: {21/2/2021, 21:31:29}"
                    ]
                }
            ]
        }
    ]
}